differintP/__init__.py
differintP/core.py
differintP/functions.py
differintP/gpu_utils.py
differintP/solvers.py
differintP/special.py
differintP/utils.py
differintP/weyl.py
differintp-0.0.4.dist-info/licenses/LICENSE
differintp-0.0.4.dist-info/METADATA
differintp-0.0.4.dist-info/WHEEL
differintp-0.0.4.dist-info/top_level.txt
differintp-0.0.4.dist-info/RECORD
