Metadata-Version: 2.4
Name: differintP
Version: 0.0.4
Summary: Modern, pure Python fractional calculus library (fork of differint)
Author-email: iparsw <parsaroshanak@gmail.com>
License: MIT License
Project-URL: Homepage, https://github.com/iparsw/differintP
Project-URL: Repository, https://github.com/iparsw/differintP
Project-URL: Issues, https://github.com/iparsw/differintP/issues
Classifier: Programming Language :: Python :: 3
Classifier: License :: OSI Approved :: MIT License
Classifier: Operating System :: OS Independent
Classifier: Intended Audience :: Science/Research
Classifier: Topic :: Scientific/Engineering :: Mathematics
Requires-Python: >=3.10
License-File: LICENSE
Requires-Dist: numpy>=1.19
Requires-Dist: scipy>=1.15.3
Requires-Dist: numba>=0.61.2
Provides-Extra: gpu
Requires-Dist: cupy; extra == "gpu"
Dynamic: license-file
